{
  "id": "MAP_MT_MOON2",
  "name": "MtMoon2",
  "layout": "LAYOUT_MT_MOON2",
  "music": "MUS_HG_MT_MOON_SQUARE",
  "region_map_section": "MAPSEC_MT_MOON",
  "requires_flash": false,
  "weather": "WEATHER_NONE",
  "map_type": "MAP_TYPE_ROUTE",
  "allow_cycling": true,
  "allow_escaping": true,
  "allow_running": false,
  "show_map_name": false,
  "battle_scene": "MAP_BATTLE_SCENE_NORMAL",
  "connections": 0,
  "object_events": [

  ],
  "warp_events": [

  ],
  "coord_events": [

  ],
  "bg_events": [

  ]
}
